<?xml version="1.0" encoding="UTF-8"?>
<!-- 福州的天气情况 -->
<xml_api_reply version="1">
    <weather module_id="0" tab_id="0" mobile_row="0" mobile_zipped="1"
        row="0" section="0">
        <forecast_information>
            <city data="Fuzhou, Fujian" />
            <postal_code data="fuzhou" />
            <latitude_e6 data="" />
            <longitude_e6 data="" />
            <forecast_date data="2011-01-08" />
            <current_date_time data="2011-01-08 23:00:00 +0000" />
            <unit_system data="SI" />
        </forecast_information>
        <current_conditions>
            <condition data="多云" />
            <temp_f data="53" />
            <temp_c data="12" />
            <humidity data="湿度： 43%" />
            <icon data="/ig/images/weather/mostly_cloudy.gif" />
            <wind_condition data="风向： 东北、风速：1 米/秒" />
        </current_conditions>
        <forecast_conditions>
            <day_of_week data="周六" />
            <low data="7" />
            <high data="14" />
            <icon data="/ig/images/weather/chance_of_rain.gif" />
            <condition data="可能有雨" />
        </forecast_conditions>
        <forecast_conditions>
            <day_of_week data="周日" />
            <low data="6" />
            <high data="12" />
            <icon data="/ig/images/weather/chance_of_rain.gif" />
            <condition data="可能有雨" />
        </forecast_conditions>
        <forecast_conditions>
            <day_of_week data="周一" />
            <low data="5" />
            <high data="10" />
            <icon data="/ig/images/weather/mostly_sunny.gif" />
            <condition data="晴间多云" />
        </forecast_conditions>
        <forecast_conditions>
            <day_of_week data="周二" />
            <low data="4" />
            <high data="8" />
            <icon data="/ig/images/weather/chance_of_rain.gif" />
            <condition data="可能有雨" />
        </forecast_conditions>
    </weather>
</xml_api_reply>